{"version":1,"resource":"file:///home/peter/Developer/nextjs/todo-service/src/ui/form.tsx","entries":[{"id":"udDO.tsx","timestamp":1722170850334},{"id":"8V3I.tsx","timestamp":1722170908373},{"id":"XBHr.tsx","timestamp":1722170918809},{"id":"xybf.tsx","timestamp":1722170929740},{"id":"OJqA.tsx","timestamp":1722170982694},{"id":"dKET.tsx","timestamp":1722171014823},{"id":"6SDD.tsx","timestamp":1722171027610},{"id":"8gVi.tsx","timestamp":1722171045573},{"id":"dD5f.tsx","timestamp":1722171060318},{"id":"CDqp.tsx","timestamp":1722171109961},{"id":"iamJ.tsx","timestamp":1722171148005},{"id":"I1Hz.tsx","timestamp":1722171170401},{"id":"M0tk.tsx","timestamp":1722171210098},{"id":"erig.tsx","timestamp":1722171233225},{"id":"EY5d.tsx","timestamp":1722171251393},{"id":"gwHz.tsx","timestamp":1722171286762},{"id":"cCmS.tsx","timestamp":1722171339966},{"id":"SJWN.tsx","timestamp":1722171386400},{"id":"dZyG.tsx","timestamp":1722171407574},{"id":"6a6u.tsx","timestamp":1722171434069},{"id":"rxwf.tsx","timestamp":1722171459806},{"id":"XTnz.tsx","timestamp":1722171510282},{"id":"H3s6.tsx","timestamp":1722171520746},{"id":"S98z.tsx","timestamp":1722171534112},{"id":"4MA4.tsx","timestamp":1722171777953},{"id":"g20n.tsx","timestamp":1722171806621},{"id":"OA7P.tsx","timestamp":1722171821417},{"id":"NBSu.tsx","timestamp":1722171846000},{"id":"fcoE.tsx","timestamp":1722171893065},{"id":"mDqg.tsx","timestamp":1722171975486},{"id":"JTVZ.tsx","timestamp":1722420038042},{"id":"1uIA.tsx","timestamp":1722420102206},{"id":"59gu.tsx","timestamp":1722420115181},{"id":"ixmJ.tsx","timestamp":1722420154373},{"id":"4KSu.tsx","timestamp":1722420191824},{"id":"4Lcp.tsx","timestamp":1722420211304},{"id":"YtQJ.tsx","timestamp":1722420222376},{"id":"IQDj.tsx","timestamp":1722420255192},{"id":"xt0x.tsx","timestamp":1722420320174},{"id":"e4EA.tsx","timestamp":1722421383821},{"id":"QcVd.tsx","timestamp":1722421394128},{"id":"RmbN.tsx","timestamp":1722421864791},{"id":"hUbq.tsx","timestamp":1722421876005},{"id":"0GVf.tsx","timestamp":1722421894066},{"id":"vswU.tsx","timestamp":1722421950989}]}